{"descargado_en": "2026-07-14T10:43:12.497044+00:00", "notas": [{"id": "a74800da4a93", "titulo": "El gas europeo alcanza máximos de un mes por tasas en el estrecho de Ormuz", "link": "https://es.investing.com/news/commodities-news/el-gas-europeo-alcanza-maximos-de-un-mes-por-tasas-en-el-estrecho-de-ormuz-3740575", "descripcion": "", "fecha_publicacion": "2026-07-14T08:53:09+00:00", "fuente_id": "investing_agro", "fuente_nombre": "Investing Agro", "categoria": "Agro"}, {"id": "19cecb87351c", "titulo": "Futuros de la plata en canal bajista a 58,52 $: Niveles en vivo", "link": "https://es.investing.com/news/commodities-news/futuros-de-la-plata-caen-293-y-presionan-soporte-clave-niveles-en-vivo-93CH-3738371", "descripcion": "", "fecha_publicacion": "2026-07-14T07:07:24+00:00", "fuente_id": "investing_agro", "fuente_nombre": "Investing Agro", "categoria": "Agro"}, {"id": "f93239ced8be", "titulo": "Futuros del oro atrapados entre 3.992 y 4.110: Niveles en vivo", "link": "https://es.investing.com/news/commodities-news/los-futuros-del-oro-testean-soporte-clave-en-4050-niveles-en-vivo-93CH-3738360", "descripcion": "", "fecha_publicacion": "2026-07-14T07:04:57+00:00", "fuente_id": "investing_agro", "fuente_nombre": "Investing Agro", "categoria": "Agro"}]}