{"descargado_en": "2026-07-11T21:07:27.478674+00:00", "notas": [{"id": "a241dd9d4fe4", "titulo": "El director ejecutivo de Eni advierte que el petróleo podría superar los 100 dólares en 2027", "link": "https://es.investing.com/news/commodities-news/el-director-ejecutivo-de-eni-advierte-que-el-petroleo-podria-superar-los-100-dolares-en-2027-3738090", "descripcion": "", "fecha_publicacion": "2026-07-11T13:25:52+00:00", "fuente_id": "investing_agro", "fuente_nombre": "Investing Agro", "categoria": "Agro"}, {"id": "24df06c7b174", "titulo": "China ordena a sus refinerías mantener alta producción ante tensiones con Irán", "link": "https://es.investing.com/news/commodities-news/china-ordena-a-sus-refinerias-mantener-alta-produccion-ante-tensiones-con-iran-3738065", "descripcion": "", "fecha_publicacion": "2026-07-11T12:07:18+00:00", "fuente_id": "investing_agro", "fuente_nombre": "Investing Agro", "categoria": "Agro"}, {"id": "5b83a34dd01a", "titulo": "Futuros de la plata atrapados en consolidación bajista: Niveles en vivo", "link": "https://es.investing.com/news/commodities-news/futuros-de-la-plata-en-resistencia-clave-niveles-en-vivo-93CH-3728341", "descripcion": "", "fecha_publicacion": "2026-07-10T19:08:09+00:00", "fuente_id": "investing_agro", "fuente_nombre": "Investing Agro", "categoria": "Agro"}]}