{"descargado_en": "2026-07-24T09:14:16.729784+00:00", "notas": [{"id": "322d442200f8", "titulo": "Tensión en Oriente Próximo; más aranceles de EE.UU.: 5 claves en Wall Street", "link": "https://es.investing.com/news/economy-news/hostilidades-en-oriente-proximo-y-nuevos-aranceles-de-eeuu-mueven-los-mercados-3757758", "descripcion": "", "fecha_publicacion": "2026-07-24T07:52:17+00:00", "fuente_id": "investing_economia", "fuente_nombre": "Investing Economía", "categoria": "Mercados"}, {"id": "817831028bed", "titulo": "La bolsa hoy: IBEX 35, Euro Dólar, petróleo y geopolítica", "link": "https://es.investing.com/news/economy-news/la-bolsa-hoy-ibex-35-euro-dolar-petroleo-y-geopolitica-3757676", "descripcion": "", "fecha_publicacion": "2026-07-24T06:47:33+00:00", "fuente_id": "investing_economia", "fuente_nombre": "Investing Economía", "categoria": "Mercados"}, {"id": "4044d353d7a8", "titulo": "Irán rechaza la propuesta de alto el fuego respaldada por EE.UU.", "link": "https://es.investing.com/news/economy-news/iran-rechaza-propuesta-de-alto-el-fuego-respaldada-por-eeuu-3757487", "descripcion": "", "fecha_publicacion": "2026-07-24T00:32:13+00:00", "fuente_id": "investing_economia", "fuente_nombre": "Investing Economía", "categoria": "Mercados"}]}