{
  "generado_en": "2026-06-12T12:19:33.935990+00:00",
  "generado_ar": "12/06/2026 09:19",
  "datos": {
    "dolar_oficial": {
      "valor": {
        "compra": 1400,
        "venta": 1450
      },
      "actualizado": "2026-06-12T12:18:14.253948+00:00",
      "stale": false,
      "unidad": "ARS",
      "fuente": "dolarapi.com",
      "frecuencia": "intradia"
    },
    "dolar_mep": {
      "valor": {
        "compra": 1448.9,
        "venta": 1454.2
      },
      "actualizado": "2026-06-12T12:18:14.345327+00:00",
      "stale": false,
      "unidad": "ARS",
      "fuente": "dolarapi.com",
      "frecuencia": "intradia"
    },
    "dolar_ccl": {
      "valor": {
        "compra": 1494,
        "venta": 1494.9
      },
      "actualizado": "2026-06-12T12:18:14.422468+00:00",
      "stale": false,
      "unidad": "ARS",
      "fuente": "dolarapi.com",
      "frecuencia": "intradia"
    },
    "dolar_blue": {
      "valor": {
        "compra": 1430,
        "venta": 1450
      },
      "actualizado": "2026-06-12T12:18:14.509487+00:00",
      "stale": false,
      "unidad": "ARS",
      "fuente": "dolarapi.com",
      "frecuencia": "intradia"
    },
    "dolar_mayorista": {
      "valor": {
        "compra": 1423.5,
        "venta": 1432.5
      },
      "actualizado": "2026-06-12T12:18:14.577045+00:00",
      "stale": false,
      "unidad": "ARS",
      "variacion": 0,
      "fuente": "dolarapi.com",
      "frecuencia": "intradia"
    },
    "dolar_tarjeta": {
      "valor": {
        "compra": 1820,
        "venta": 1885
      },
      "actualizado": "2026-06-12T12:18:14.658265+00:00",
      "stale": false,
      "unidad": "ARS",
      "fuente": "dolarapi.com",
      "frecuencia": "intradia"
    },
    "dolar_cripto": {
      "valor": {
        "compra": 1498.2,
        "venta": 1498.3
      },
      "actualizado": "2026-06-12T12:18:14.713091+00:00",
      "stale": false,
      "unidad": "ARS",
      "fuente": "dolarapi.com",
      "frecuencia": "intradia"
    },
    "brecha_mep": {
      "valor": 0.3,
      "actualizado": "2026-06-12T12:18:14.713118+00:00",
      "stale": false,
      "unidad": "%",
      "fuente": "cálculo PPA",
      "frecuencia": "intradia"
    },
    "riesgo_pais": {
      "valor": 503,
      "actualizado": "2026-06-12T12:18:14.993030+00:00",
      "stale": false,
      "unidad": "pb",
      "fecha": "2026-06-10",
      "variacion": 1.0,
      "fuente": "argentinadatos.com",
      "frecuencia": "intradia"
    },
    "banda": {
      "valor": {
        "piso": 782,
        "techo": 1781,
        "dolar": 1432,
        "posicion": 65.1
      },
      "actualizado": "2026-06-12T12:19:28.432207+00:00",
      "stale": false,
      "fuente": "cálculo PPA (esquema BCRA)",
      "frecuencia": "diaria"
    },
    "reservas": {
      "valor": 47834.0,
      "actualizado": "2026-06-12T12:18:15.924744+00:00",
      "stale": false,
      "unidad": "MM USD",
      "fecha": "2026-06-09",
      "variacion": 0.07,
      "fuente": "BCRA API v4",
      "frecuencia": "diaria"
    },
    "ipc_mensual": {
      "valor": 2.8,
      "actualizado": "2026-06-12T12:19:29.735763+00:00",
      "stale": false,
      "unidad": "%",
      "fecha": "2026-04-01",
      "periodo": "2026-04",
      "fuente": "datos.gob.ar",
      "frecuencia": "mensual"
    },
    "ipc_nucleo": {
      "valor": 2.3,
      "actualizado": "2026-06-12T12:19:31.604000+00:00",
      "stale": false,
      "unidad": "%",
      "fecha": "2026-04-01",
      "periodo": "2026-04",
      "fuente": "datos.gob.ar",
      "frecuencia": "mensual"
    },
    "emae": {
      "valor": 158.65,
      "actualizado": "2026-06-12T12:19:32.775761+00:00",
      "stale": false,
      "unidad": "puntos",
      "fecha": "2026-03-01",
      "periodo": "2026-03",
      "fuente": "datos.gob.ar",
      "frecuencia": "mensual"
    },
    "tcrm": {
      "valor": 1415.0,
      "actualizado": "2026-06-12T12:19:33.935965+00:00",
      "stale": false,
      "unidad": "índice",
      "fecha": "2026-03-17",
      "periodo": "2026-03",
      "fuente": "datos.gob.ar",
      "frecuencia": "diaria"
    },
    "base_monetaria": {
      "valor": 41830730.0,
      "actualizado": "2026-06-11T22:17:22.938291+00:00",
      "stale": true,
      "unidad": "MM $",
      "fecha": "2026-06-09",
      "variacion": -1.35,
      "fuente": "BCRA API v4",
      "frecuencia": "diaria"
    },
    "m2_privado": {
      "valor": 24232702.0,
      "actualizado": "2026-06-11T22:17:24.140825+00:00",
      "stale": true,
      "unidad": "MM $",
      "fecha": "2026-06-09",
      "variacion": 0.14,
      "fuente": "BCRA API v4",
      "frecuencia": "diaria"
    },
    "call_baibar": {
      "valor": 2.0,
      "actualizado": "2026-06-12T12:19:26.955135+00:00",
      "stale": false,
      "unidad": "% TNA",
      "fecha": "2026-05-31",
      "variacion": -23.08,
      "fuente": "BCRA API v4",
      "frecuencia": "diaria"
    },
    "circulacion": {
      "valor": 20.0,
      "actualizado": "2026-06-12T12:19:27.762695+00:00",
      "stale": false,
      "unidad": "MM $",
      "fecha": "2026-06-10",
      "variacion": -1.84,
      "fuente": "BCRA API v4",
      "frecuencia": "diaria"
    },
    "uva": {
      "valor": 23.0,
      "actualizado": "2026-06-12T12:19:28.426635+00:00",
      "stale": false,
      "unidad": "índice",
      "fecha": "2026-05-31",
      "variacion": -4.96,
      "fuente": "BCRA API v4",
      "frecuencia": "diaria"
    }
  }
}