{
  "generado_en": "2026-07-23T18:12:47.061957+00:00",
  "generado_ar": "23/07/2026 15:12",
  "datos": {
    "dolar_oficial": {
      "valor": {
        "compra": 1465,
        "venta": 1515
      },
      "actualizado": "2026-07-23T18:12:38.823993+00:00",
      "stale": false,
      "unidad": "ARS",
      "fuente": "dolarapi.com",
      "frecuencia": "intradia"
    },
    "dolar_mep": {
      "valor": {
        "compra": 1517.8,
        "venta": 1519.4
      },
      "actualizado": "2026-07-23T18:12:38.886507+00:00",
      "stale": false,
      "unidad": "ARS",
      "fuente": "dolarapi.com",
      "frecuencia": "intradia"
    },
    "dolar_ccl": {
      "valor": {
        "compra": 1580.6,
        "venta": 1581.1
      },
      "actualizado": "2026-07-23T18:12:38.937625+00:00",
      "stale": false,
      "unidad": "ARS",
      "fuente": "dolarapi.com",
      "frecuencia": "intradia"
    },
    "dolar_blue": {
      "valor": {
        "compra": 1540,
        "venta": 1560
      },
      "actualizado": "2026-07-23T18:12:38.988930+00:00",
      "stale": false,
      "unidad": "ARS",
      "fuente": "dolarapi.com",
      "frecuencia": "intradia"
    },
    "dolar_mayorista": {
      "valor": {
        "compra": 1482,
        "venta": 1491
      },
      "actualizado": "2026-07-23T18:12:39.051245+00:00",
      "stale": false,
      "unidad": "ARS",
      "fuente": "dolarapi.com",
      "frecuencia": "intradia"
    },
    "dolar_tarjeta": {
      "valor": {
        "compra": 1904.5,
        "venta": 1969.5
      },
      "actualizado": "2026-07-23T18:12:39.138136+00:00",
      "stale": false,
      "unidad": "ARS",
      "fuente": "dolarapi.com",
      "frecuencia": "intradia"
    },
    "dolar_cripto": {
      "valor": {
        "compra": 1576.5,
        "venta": 1579.27
      },
      "actualizado": "2026-07-23T18:12:39.188750+00:00",
      "stale": false,
      "unidad": "ARS",
      "fuente": "dolarapi.com",
      "frecuencia": "intradia"
    },
    "brecha_mep": {
      "valor": 0.3,
      "actualizado": "2026-07-23T18:12:39.188783+00:00",
      "stale": false,
      "unidad": "%",
      "fuente": "cálculo PPA",
      "frecuencia": "intradia"
    },
    "riesgo_pais": {
      "valor": 421,
      "actualizado": "2026-07-23T18:12:40.129236+00:00",
      "stale": false,
      "unidad": "pb",
      "fecha": "2026-07-21",
      "variacion": 1.2,
      "fuente": "argentinadatos.com",
      "frecuencia": "intradia",
      "modo": "automatico"
    },
    "banda": {
      "valor": {
        "piso": 755,
        "techo": 1844,
        "dolar": 1491,
        "posicion": 67.6
      },
      "actualizado": "2026-07-23T18:12:47.061942+00:00",
      "stale": false,
      "fuente": "cálculo PPA (esquema BCRA)",
      "frecuencia": "diaria"
    },
    "reservas": {
      "valor": 48809.0,
      "actualizado": "2026-07-23T18:12:41.035525+00:00",
      "stale": false,
      "unidad": "MM USD",
      "fecha": "2026-07-20",
      "variacion": 0.04,
      "fuente": "BCRA API v4",
      "frecuencia": "diaria"
    },
    "ipc_mensual": {
      "valor": 1.9,
      "actualizado": "2026-07-23T15:25:24.268688+00:00",
      "stale": false,
      "unidad": "%",
      "fecha": "2026-06-01",
      "periodo": "2026-06",
      "fuente": "datos.gob.ar",
      "frecuencia": "mensual"
    },
    "ipc_nucleo": {
      "valor": 1.6,
      "actualizado": "2026-07-23T15:25:24.969581+00:00",
      "stale": false,
      "unidad": "%",
      "fecha": "2026-06-01",
      "periodo": "2026-06",
      "fuente": "datos.gob.ar",
      "frecuencia": "mensual"
    },
    "emae": {
      "valor": 165.47,
      "actualizado": "2026-07-23T15:25:25.680383+00:00",
      "stale": false,
      "unidad": "puntos",
      "fecha": "2026-05-01",
      "periodo": "2026-05",
      "fuente": "datos.gob.ar",
      "frecuencia": "mensual"
    },
    "tcrm": {
      "valor": 1460.0,
      "actualizado": "2026-07-23T15:25:25.925067+00:00",
      "stale": false,
      "unidad": "índice",
      "fecha": "2026-06-17",
      "periodo": "2026-06",
      "fuente": "datos.gob.ar",
      "frecuencia": "diaria"
    },
    "base_monetaria": {
      "valor": 45661395.0,
      "actualizado": "2026-07-23T18:12:43.487963+00:00",
      "stale": false,
      "unidad": "MM $",
      "fecha": "2026-07-20",
      "variacion": 1.35,
      "fuente": "BCRA API v4",
      "frecuencia": "diaria"
    },
    "m2_privado": {
      "valor": 26361562.0,
      "actualizado": "2026-07-23T18:12:44.387385+00:00",
      "stale": false,
      "unidad": "MM $",
      "fecha": "2026-07-20",
      "variacion": -0.05,
      "fuente": "BCRA API v4",
      "frecuencia": "diaria"
    },
    "call_baibar": {
      "valor": 2.0,
      "actualizado": "2026-07-23T18:12:45.164714+00:00",
      "stale": false,
      "unidad": "% TNA",
      "fecha": "2026-06-30",
      "variacion": -4.76,
      "fuente": "BCRA API v4",
      "frecuencia": "diaria"
    },
    "circulacion": {
      "valor": 22.0,
      "actualizado": "2026-07-23T18:12:46.092654+00:00",
      "stale": false,
      "unidad": "MM $",
      "fecha": "2026-07-21",
      "variacion": 4.14,
      "fuente": "BCRA API v4",
      "frecuencia": "diaria"
    },
    "uva": {
      "valor": 22.0,
      "actualizado": "2026-07-23T18:12:46.996900+00:00",
      "stale": false,
      "unidad": "índice",
      "fecha": "2026-06-30",
      "variacion": -5.58,
      "fuente": "BCRA API v4",
      "frecuencia": "diaria"
    }
  }
}